sptbuild/__init__.py
sptbuild/__main__.py
sptbuild/bundler.py
sptbuild/lib.py
sptbuild/plugin_config.py
sptbuild/commands/__init__.py
sptbuild/commands/init_config.py
sptbuild/commands/init_csproj.py
sptbuild/commands/package.py
sptbuild/commands/release.py
sptbuild/commands/setup_ci.py
sptbuild/commands/upload.py
sptbuild-0.1.4.dist-info/licenses/LICENSE.md
sptbuild-0.1.4.dist-info/METADATA
sptbuild-0.1.4.dist-info/WHEEL
sptbuild-0.1.4.dist-info/entry_points.txt
sptbuild-0.1.4.dist-info/top_level.txt
sptbuild-0.1.4.dist-info/RECORD
