Metadata-Version: 2.4
Name: sptbuild
Version: 0.1.4
Summary: Build and release tool for SPT client plugins
Author-email: flir <flir.063ur@passmail.net>
License: MIT
Project-URL: Homepage, https://gitlab.com/flir063-spt/sptbuild
Project-URL: Issues, https://gitlab.com/flir063-spt/sptbuild/-/issues
Keywords: spt,tarkov,bepinex,plugin,build,gitlab
Classifier: Development Status :: 4 - Beta
Classifier: Intended Audience :: Developers
Classifier: Programming Language :: Python :: 3
Classifier: Programming Language :: Python :: 3.8
Classifier: Programming Language :: Python :: 3.9
Classifier: Programming Language :: Python :: 3.10
Classifier: Programming Language :: Python :: 3.11
Classifier: Programming Language :: Python :: 3.12
Requires-Python: >=3.8
License-File: LICENSE.md
Requires-Dist: requests>=2.31.0
Requires-Dist: semver>=3.0.0
Provides-Extra: dev
Requires-Dist: towncrier>=23.11.0; extra == "dev"
Requires-Dist: pytest>=7.0.0; extra == "dev"
Requires-Dist: pytest-cov>=4.0.0; extra == "dev"
Requires-Dist: build>=1.0.0; extra == "dev"
Requires-Dist: twine>=4.0.0; extra == "dev"
Dynamic: license-file
